DanpianjiJiaochengCYuyanBianchengWang/README.md
DanpianjiJiaochengCYuyanBianchengWang/__init__.py
DanpianjiJiaochengCYuyanBianchengWang/__main__.py
DanpianjiJiaochengCYuyanBianchengWang/file.epub
DanpianjiJiaochengCYuyanBianchengWang/index.html
DanpianjiJiaochengCYuyanBianchengWang/css/__init__.py
DanpianjiJiaochengCYuyanBianchengWang/css/annotations.css
DanpianjiJiaochengCYuyanBianchengWang/css/main.css
DanpianjiJiaochengCYuyanBianchengWang/css/normalize.css
DanpianjiJiaochengCYuyanBianchengWang/css/popup.css
DanpianjiJiaochengCYuyanBianchengWang/font/__init__.py
DanpianjiJiaochengCYuyanBianchengWang/font/fontello.eot
DanpianjiJiaochengCYuyanBianchengWang/font/fontello.svg
DanpianjiJiaochengCYuyanBianchengWang/font/fontello.ttf
DanpianjiJiaochengCYuyanBianchengWang/font/fontello.woff
DanpianjiJiaochengCYuyanBianchengWang/img/__init__.py
DanpianjiJiaochengCYuyanBianchengWang/img/annotator-glyph-sprite.png
DanpianjiJiaochengCYuyanBianchengWang/img/annotator-icon-sprite.png
DanpianjiJiaochengCYuyanBianchengWang/img/apple-touch-icon.png
DanpianjiJiaochengCYuyanBianchengWang/img/cancelfullscreen.png
DanpianjiJiaochengCYuyanBianchengWang/img/close.png
DanpianjiJiaochengCYuyanBianchengWang/img/fullscreen.png
DanpianjiJiaochengCYuyanBianchengWang/img/loader.gif
DanpianjiJiaochengCYuyanBianchengWang/img/menu-icon.png
DanpianjiJiaochengCYuyanBianchengWang/img/save.png
DanpianjiJiaochengCYuyanBianchengWang/img/saved.png
DanpianjiJiaochengCYuyanBianchengWang/img/settings-s.png
DanpianjiJiaochengCYuyanBianchengWang/img/settings.png
DanpianjiJiaochengCYuyanBianchengWang/img/star.png
DanpianjiJiaochengCYuyanBianchengWang/js/__init__.py
DanpianjiJiaochengCYuyanBianchengWang/js/epub.js
DanpianjiJiaochengCYuyanBianchengWang/js/epub.min.js
DanpianjiJiaochengCYuyanBianchengWang/js/epub.min.map
DanpianjiJiaochengCYuyanBianchengWang/js/hooks.min.js
DanpianjiJiaochengCYuyanBianchengWang/js/hooks.min.map
DanpianjiJiaochengCYuyanBianchengWang/js/reader.js
danpianji_jiaocheng_c_yuyan_biancheng_wang-2024.3.2.0.dist-info/METADATA
danpianji_jiaocheng_c_yuyan_biancheng_wang-2024.3.2.0.dist-info/WHEEL
danpianji_jiaocheng_c_yuyan_biancheng_wang-2024.3.2.0.dist-info/entry_points.txt
danpianji_jiaocheng_c_yuyan_biancheng_wang-2024.3.2.0.dist-info/top_level.txt
danpianji_jiaocheng_c_yuyan_biancheng_wang-2024.3.2.0.dist-info/RECORD
